MANIFEST.in
README.rst
README.txt
beyondskins.responsive-full.png
beyondskins.responsive-reduced.png
beyondskins.responsive.zip
setup.cfg
setup.py
beyondskins/__init__.py
beyondskins.responsive.egg-info/PKG-INFO
beyondskins.responsive.egg-info/SOURCES.txt
beyondskins.responsive.egg-info/dependency_links.txt
beyondskins.responsive.egg-info/entry_points.txt
beyondskins.responsive.egg-info/namespace_packages.txt
beyondskins.responsive.egg-info/not-zip-safe
beyondskins.responsive.egg-info/requires.txt
beyondskins.responsive.egg-info/top_level.txt
beyondskins/responsive/__init__.py
beyondskins/responsive/configure.zcml
beyondskins/responsive/version.txt
beyondskins/responsive/theme/beyondskins.responsive/index.html
beyondskins/responsive/theme/beyondskins.responsive/manifest.cfg
beyondskins/responsive/theme/beyondskins.responsive/rules.xml
beyondskins/responsive/theme/beyondskins.responsive/static/bg.jpg
beyondskins/responsive/theme/beyondskins.responsive/static/favicon.ico
beyondskins/responsive/theme/beyondskins.responsive/static/function.js
beyondskins/responsive/theme/beyondskins.responsive/static/header.png
beyondskins/responsive/theme/beyondskins.responsive/static/my-logo.png
beyondskins/responsive/theme/beyondskins.responsive/static/search-ico.png
beyondskins/responsive/theme/beyondskins.responsive/static/sections-ico.png
beyondskins/responsive/theme/beyondskins.responsive/static/style.css
beyondskins/responsive/theme/beyondskins.responsive/static/touch_icon.png
docs/HISTORY.txt